{
  "url": "https://www.mondou.com/fr-CA/",
  "title": "Mondou Search",
  "logfile": "output/Mondou.log",
  "randomScripts": [
    "RECORDER",
    "RECORDER"
  ],
  "randomScripts2": [
    "searchAndOpen2x",
    "searchAndClick",
    "searchAndOpen2x",
    "searchAndChangeTab"
  ],
  "randomKeywords": [
    "accountfeed",
    "account",
    "lightning",
    "report",
    "chatter",
    "chatterfeed"
  ],
  "scriptKeywords": [
    {
      "script": "searchSpecial1",
      "keyword": "exchange"
    },
    {
      "script": "searchSpecial1",
      "keyword": "exchange feed"
    },
    {
      "script": "searchSpecial2",
      "keyword": "account"
    }
  ],
  "username": "",
  "password": ""
}